{
    "canvas": {
        "gridx": 1,
        "gridy": 1,
        "size": 6
    },
    "multiplot": {
        "input/EPOS-LHC16.root/QualTender/hClusterEvsTM%d": {
            "normalize": 1,
            "oname": "results/epos-timing.pdf",
            "option": "colz",
            "separate": ""
        },
        "input/Pythia-LHC16.root/QualTender/hClusterEvsTM%d": {
            "normalize": 1,
            "oname": "results/pythia-timing.pdf",
            "option": "colz",
            "separate": ""
        }
    }
}
